Metadata-Version: 2.1
Name: OlxPy
Version: 0.0.1
Summary: This package simplifies the extraction of data from OLX websites.
Home-page: https://github.com/Vladislavus1/OlxPyApi
Author: Vladislavus1
Author-email: vlydgames@gmail.com
Requires-Dist: beautifulsoup4==4.12.3
Requires-Dist: requests==2.31.0
Requires-Dist: lxml==5.2.2
